[
  {
    "id": "48714643-7060-410c-9463-aba22a30135a",
    "title": "Side A",
    "slug": "side-a",
    "description": "",
    "philosophy": "",
    "schedule": "",
    "vibes": [],
    "coverColor": "#c90300",
    "coverImage": "",
    "createdAt": "2026-03-28T20:41:19.479Z",
    "updatedAt": "2026-03-29T00:51:24.286Z",
    "_count": {
      "songs": 90
    }
  },
  {
    "id": "e3c8eb92-a2e5-4aa1-b60a-b44ded1f6821",
    "title": "test duplikat",
    "slug": "test-duplikat",
    "description": "",
    "philosophy": "",
    "schedule": "",
    "vibes": [],
    "coverColor": "#3b82f6",
    "coverImage": "",
    "createdAt": "2026-03-27T15:32:35.929Z",
    "updatedAt": "2026-03-27T15:32:35.929Z",
    "_count": {
      "songs": 2
    }
  },
  {
    "id": "42481e26-549a-4d86-be7b-c23241a99f1f",
    "title": "Melajoe",
    "slug": "malay",
    "description": "",
    "philosophy": "",
    "schedule": "",
    "vibes": [],
    "coverColor": "#3b82f6",
    "coverImage": "",
    "createdAt": "2026-03-25T10:12:37.997Z",
    "updatedAt": "2026-03-28T20:57:52.746Z",
    "_count": {
      "songs": 17
    }
  },
  {
    "id": "0454be2b-6ef2-4f67-b9e8-87204a400ff3",
    "title": "International Favorites",
    "slug": "international-favorites",
    "description": "Top global tracks that define the current era.",
    "philosophy": "Music is a universal language, connecting us across borders.",
    "schedule": "Anytime",
    "vibes": [
      "International",
      "Global",
      "Hits"
    ],
    "coverColor": "#1d4ed8",
    "coverImage": "/images/playlists/playlist_international.webp",
    "createdAt": "2026-03-16T16:15:12.980Z",
    "updatedAt": "2026-03-22T12:31:20.375Z",
    "_count": {
      "songs": 88
    }
  },
  {
    "id": "736ce0c5-f8dd-44bc-8a70-1ead28e3b10d",
    "title": "Indo Hits",
    "slug": "indo-hits",
    "description": "Koleksi lagu-lagu terbaik dari tanah air dan sekitarnya.",
    "philosophy": "Nada-nada yang kental sama rasa bangga dan memori lokal.",
    "schedule": "Relaxing",
    "vibes": [
      "Indo",
      "Pop",
      "Local"
    ],
    "coverColor": "#991b1b",
    "coverImage": "/images/playlists/playlist_indo_hits.webp",
    "createdAt": "2026-03-16T16:15:12.140Z",
    "updatedAt": "2026-03-22T12:31:19.005Z",
    "_count": {
      "songs": 296
    }
  },
  {
    "id": "51c524a3-135b-4139-8cbc-842b7e85c8b7",
    "title": "hi, long time no see.",
    "slug": "tentang-dia",
    "description": "いってらっしゃい",
    "philosophy": "Kenangan itu cara kita megang erat hal-hal yang kita cinta, tentang siapa kita, dan hal yang nggak pengen kita lepasin.",
    "schedule": "Late Night / Rainy",
    "vibes": [
      "Nostalgic",
      "Love",
      "Acoustic"
    ],
    "coverColor": "#ff4015",
    "coverImage": "/images/playlists/playlist_tentang_dia_final.webp",
    "createdAt": "2026-03-03T16:18:58.327Z",
    "updatedAt": "2026-03-27T20:03:43.395Z",
    "_count": {
      "songs": 65
    }
  },
  {
    "id": "77c65905-4a66-4fa9-8bf4-4980701a9059",
    "title": "Malay",
    "slug": "menunggu-pagi",
    "description": "",
    "philosophy": "Setiap sunrise itu kayak undangan buatikin harinya seseorang jadi lebih cerah.",
    "schedule": "5 AM - 9 AM",
    "vibes": [
      "Hopeful",
      "Morning",
      "Pop"
    ],
    "coverColor": "#f59e0b",
    "coverImage": "/images/playlists/playlist_menunggu_pagi_final.webp",
    "createdAt": "2026-03-03T16:18:49.843Z",
    "updatedAt": "2026-03-27T10:20:43.947Z",
    "_count": {
      "songs": 17
    }
  },
  {
    "id": "5854d37a-a782-451e-bfbc-1d2105397d2a",
    "title": "Alexandria",
    "slug": "line-up-inti",
    "description": "",
    "philosophy": "Soundtrack buat momen-momen main character kamu. Energi yang bikin bintang tetep bersinar.",
    "schedule": "Anytime",
    "vibes": [
      "Epic",
      "Main Character",
      "Energy"
    ],
    "coverColor": "#7c3aed",
    "coverImage": "/images/playlists/playlist_line_up_inti_final.webp",
    "createdAt": "2026-03-03T16:18:32.041Z",
    "updatedAt": "2026-03-27T22:39:23.501Z",
    "_count": {
      "songs": 54
    }
  },
  {
    "id": "701e28c3-2d31-4b9b-a993-381df53f70b1",
    "title": "Western Classic",
    "slug": "teman-sunyi",
    "description": "Melodi pelan buat nemenin malam-malam tanpa tidur di bawah bintang.",
    "philosophy": "Dalam sunyinya malam, kadang kita ktemu jawaban yang nggak bisa didengar pas siangnya lagi berisik.",
    "schedule": "11 PM - 3 AM",
    "vibes": [
      "Melancholic",
      "Space",
      "Introspective"
    ],
    "coverColor": "#1e3a8a",
    "coverImage": "/images/playlists/playlist_teman_sunyi_final.webp",
    "createdAt": "2026-03-03T16:18:14.184Z",
    "updatedAt": "2026-03-22T12:31:13.022Z",
    "_count": {
      "songs": 0
    }
  }
]