[
    {
        "time": 8.16,
        "text": "I've been reading books of old"
    },
    {
        "time": 10.53,
        "text": "The legends and the myths"
    },
    {
        "time": 12.82,
        "text": "Achilles and his gold"
    },
    {
        "time": 14.94,
        "text": "Hercules and his gifts"
    },
    {
        "time": 17.49,
        "text": "Spiderman's control"
    },
    {
        "time": 19.85,
        "text": "And Batman with his fists"
    },
    {
        "time": 22.02,
        "text": "And clearly I don't see myself upon that list"
    },
    {
        "time": 26.32,
        "text": "She said 'Where'd you wanna go?"
    },
    {
        "time": 29.1,
        "text": "How much you wanna risk?"
    },
    {
        "time": 31.09,
        "text": "I'm not looking for somebody"
    },
    {
        "time": 33.38,
        "text": "With some superhuman gifts"
    },
    {
        "time": 35.8,
        "text": "Some superhero"
    },
    {
        "time": 37.91,
        "text": "Some fairytale bliss"
    },
    {
        "time": 40.46,
        "text": "Just something I can turn to"
    },
    {
        "time": 42.76,
        "text": "Somebody I can kiss'"
    },
    {
        "time": 45.03,
        "text": "I want something just like this"
    },
    {
        "time": 47.42,
        "text": "Doo-doo-doo, doo-doo-doo"
    },
    {
        "time": 49.53,
        "text": "Doo-doo-doo, doo-doo"
    },
    {
        "time": 51.77,
        "text": "Doo-doo-doo, doo-doo-doo"
    },
    {
        "time": 54.19,
        "text": "Oh, I want something just like this"
    },
    {
        "time": 56.62,
        "text": "Doo-doo-doo, doo-doo-doo"
    },
    {
        "time": 58.79,
        "text": "Doo-doo-doo, doo-doo"
    },
    {
        "time": 60.96,
        "text": "Doo-doo-doo, doo-doo-doo'"
    },
    {
        "time": 63.56,
        "text": "Oh, I want something just like this"
    },
    {
        "time": 71.95,
        "text": "I want something just like this"
    },
    {
        "time": 82.62,
        "text": "I've been reading books of old"
    },
    {
        "time": 84.63,
        "text": "The legends and the myths"
    },
    {
        "time": 86.79,
        "text": "The testaments they told"
    },
    {
        "time": 88.96,
        "text": "The moon and its eclipse"
    },
    {
        "time": 91.39,
        "text": "And Superman unrolls"
    },
    {
        "time": 93.87,
        "text": "A suit before he lifts"
    },
    {
        "time": 96.36,
        "text": "But I'm not the kind of person that it fits"
    },
    {
        "time": 100.89,
        "text": "She said 'Where'd you wanna go?"
    },
    {
        "time": 103.32,
        "text": "How much you wanna risk?"
    },
    {
        "time": 105.24,
        "text": "I'm not looking for somebody"
    },
    {
        "time": 107.79,
        "text": "With some superhuman gifts"
    },
    {
        "time": 110.03,
        "text": "Some superhero"
    },
    {
        "time": 112.14,
        "text": "Some fairytale bliss"
    },
    {
        "time": 114.74,
        "text": "Just something I can turn to"
    },
    {
        "time": 117.04,
        "text": "Somebody I can miss"
    },
    {
        "time": 119.4,
        "text": "I want something just like this"
    },
    {
        "time": 128.22,
        "text": "I want something just like this"
    },
    {
        "time": 137.42,
        "text": "Oh, I want something just like this"
    },
    {
        "time": 140.52,
        "text": "Doo-doo-doo, doo-doo-doo"
    },
    {
        "time": 142.38,
        "text": "Doo-doo-doo, doo-doo"
    },
    {
        "time": 144.5,
        "text": "Doo-doo-doo, doo-doo-doo"
    },
    {
        "time": 147.17,
        "text": "Oh, I want something just like this"
    },
    {
        "time": 149.47,
        "text": "Doo-doo-doo, doo-doo-doo"
    },
    {
        "time": 151.77,
        "text": "Doo-doo-doo, doo-doo"
    },
    {
        "time": 153.69,
        "text": "Doo-doo-doo, doo-doo-doo'"
    },
    {
        "time": 156.92,
        "text": "Where d'ya wanna go?"
    },
    {
        "time": 158.73,
        "text": "How much you wanna risk?"
    },
    {
        "time": 160.71,
        "text": "I'm not looking for somebody"
    },
    {
        "time": 163.31,
        "text": "With some superhuman gifts"
    },
    {
        "time": 165.61,
        "text": "Some superhero"
    },
    {
        "time": 167.66,
        "text": "Some fairytale bliss"
    },
    {
        "time": 170.15,
        "text": "Just something I can turn to"
    },
    {
        "time": 172.69,
        "text": "Somebody I can kiss"
    },
    {
        "time": 174.87,
        "text": "I want something just like this"
    },
    {
        "time": 192.94,
        "text": "Oh, I want something just like this"
    },
    {
        "time": 211.55,
        "text": "Oh, I want something just like this"
    },
    {
        "time": 229.72,
        "text": "Oh, I want something just like this"
    }
]
